receiptparser/__init__.py
receiptparser/config.py
receiptparser/parser.py
receiptparser/receipt.py
receiptparser/util.py
receiptparser/version.py
receiptparser/data/configs/germany.yml
receiptparser-1.1.data/scripts/receiptparser
tests/__init__.py
tests/test_parser.py
receiptparser-1.1.dist-info/COPYING
receiptparser-1.1.dist-info/METADATA
receiptparser-1.1.dist-info/WHEEL
receiptparser-1.1.dist-info/top_level.txt
receiptparser-1.1.dist-info/RECORD
